neon_utterance_normalizer_plugin/__init__.py
neon_utterance_normalizer_plugin-1.0.0.dist-info/LICENSE.md
neon_utterance_normalizer_plugin-1.0.0.dist-info/METADATA
neon_utterance_normalizer_plugin-1.0.0.dist-info/WHEEL
neon_utterance_normalizer_plugin-1.0.0.dist-info/entry_points.txt
neon_utterance_normalizer_plugin-1.0.0.dist-info/top_level.txt
neon_utterance_normalizer_plugin-1.0.0.dist-info/zip-safe
neon_utterance_normalizer_plugin-1.0.0.dist-info/RECORD
