Metadata-Version: 2.1
Name: neon-utterance-normalizer-plugin
Version: 1.0.0
Summary: An utterance normalizer plugin for ovos/neon/mycroft
Home-page: https://github.com/NeonGeckoCom/neon_utterance_normalizer_plugin
Author: Neongecko
Author-email: developers@neon.ai
License: bsd3
Keywords: mycroft plugin utterance parser/classifier/transformer
License-File: LICENSE.md
Requires-Dist: neon-transformers~=1.0
Requires-Dist: ovos-lingua-franca~=0.4
